MEA_analyzer_jesseantonissen/__init__.py
MEA_analyzer_jesseantonissen/library_functions.py
definitive_pipeline/__init__.py
definitive_pipeline/library_functions.py
MEA_analyzer_jesseantonissen-0.0.9.dist-info/LICENSE
MEA_analyzer_jesseantonissen-0.0.9.dist-info/METADATA
MEA_analyzer_jesseantonissen-0.0.9.dist-info/WHEEL
MEA_analyzer_jesseantonissen-0.0.9.dist-info/top_level.txt
MEA_analyzer_jesseantonissen-0.0.9.dist-info/RECORD
